musictool/__init__.py
musictool/card.py
musictool/chord.py
musictool/config.py
musictool/note.py
musictool/noterange.py
musictool/noteset.py
musictool/piano.py
musictool/pitch.py
musictool/progression.py
musictool/rhythm.py
musictool/scale.py
musictool/midi/__init__.py
musictool/midi/parse.py
musictool/midi/player.py
musictool/util/__init__.py
musictool/util/cache.py
musictool/util/etc.py
musictool/util/sequence_builder.py
musictool/util/typeguards.py
musictool/voice_leading/__init__.py
musictool/voice_leading/checks.py
musictool/voice_leading/transition.py
musictool/voice_leading/util.py
musictool-1.7.0.dist-info/METADATA
musictool-1.7.0.dist-info/WHEEL
musictool-1.7.0.dist-info/top_level.txt
musictool-1.7.0.dist-info/RECORD
