Metadata-Version: 2.1
Name: musictool
Version: 1.7.0
Summary: set of tools to work with scales, modes, modulations, chord progressions, voice leading, rhythm and more
Home-page: https://github.com/tandav/musictool
Author: Alexander Rodionov
Author-email: tandav@tandav.me
Classifier: Programming Language :: Python :: 3
Classifier: Programming Language :: Python :: 3 :: Only
Requires-Python: >=3.10
Requires-Dist: colortool (==0.2.0)
Requires-Dist: mido (>=1.2.10)
Requires-Dist: pipe21 (>=1.0.9)
Requires-Dist: tqdm (>=4.63.0)
Provides-Extra: dev
Requires-Dist: autoflake ; extra == 'dev'
Requires-Dist: autopep8 ; extra == 'dev'
Requires-Dist: bumpver ; extra == 'dev'
Requires-Dist: flake8 ; extra == 'dev'
Requires-Dist: force-absolute-imports (==0.11.0) ; extra == 'dev'
Requires-Dist: hypothesis ; extra == 'dev'
Requires-Dist: ipykernel ; extra == 'dev'
Requires-Dist: isort ; extra == 'dev'
Requires-Dist: mypy ; extra == 'dev'
Requires-Dist: no-init (==0.2.0) ; extra == 'dev'
Requires-Dist: pre-commit ; extra == 'dev'
Requires-Dist: pytest ; extra == 'dev'
Requires-Dist: pytest-asyncio ; extra == 'dev'
Requires-Dist: pytest-cov ; extra == 'dev'
